autoreject/__init__.py
autoreject/autoreject.py
autoreject/bayesopt.py
autoreject/conftest.py
autoreject/ransac.py
autoreject/utils.py
autoreject-0.4.3.dist-info/LICENSE
autoreject-0.4.3.dist-info/METADATA
autoreject-0.4.3.dist-info/WHEEL
autoreject-0.4.3.dist-info/top_level.txt
autoreject-0.4.3.dist-info/RECORD
