Metadata-Version: 2.1
Name: autoreject
Version: 0.4.3
Summary: Automated rejection and repair of epochs in M/EEG.
Home-page: http://autoreject.github.io/
Download-URL: https://github.com/autoreject/autoreject.git
Maintainer: Mainak Jas
Maintainer-email: mainakjas@gmail.com
License: BSD-3-Clause
Project-URL: Documentation, http://autoreject.github.io/
Project-URL: Bug Reports, https://github.com/autoreject/autoreject/issues
Project-URL: Source, https://github.com/autoreject/autoreject
Keywords: electroencephalography eeg magnetoencephalography meg preprocessing analysis
Platform: any
Classifier: Intended Audience :: Science/Research
Classifier: Intended Audience :: Developers
Classifier: License :: OSI Approved
Classifier: Programming Language :: Python
Classifier: Topic :: Software Development
Classifier: Topic :: Scientific/Engineering
Classifier: Operating System :: Microsoft :: Windows
Classifier: Operating System :: POSIX
Classifier: Operating System :: Unix
Classifier: Operating System :: MacOS
Classifier: Programming Language :: Python :: 3
Requires-Python: ~=3.8
License-File: LICENSE
Requires-Dist: numpy>=1.20.2
Requires-Dist: scipy>=1.6.3
Requires-Dist: mne[hdf5]>=1.0
Requires-Dist: scikit-learn>=0.24.2
Requires-Dist: joblib
Requires-Dist: matplotlib>=3.4.0
Provides-Extra: test
Requires-Dist: mne_qt_browser; extra == "test"
Requires-Dist: PyQt6; extra == "test"
Requires-Dist: pytest; extra == "test"
Requires-Dist: pytest-cov; extra == "test"
Requires-Dist: pytest-sugar; extra == "test"
Requires-Dist: check-manifest; extra == "test"
Requires-Dist: flake8; extra == "test"
Requires-Dist: importlib_resources; extra == "test"
Provides-Extra: doc
Requires-Dist: sphinx; extra == "doc"
Requires-Dist: sphinx-gallery; extra == "doc"
Requires-Dist: pydata-sphinx-theme; extra == "doc"
Requires-Dist: sphinx-copybutton; extra == "doc"
Requires-Dist: sphinx-github-role; extra == "doc"
Requires-Dist: numpydoc; extra == "doc"
Requires-Dist: cython; extra == "doc"
Requires-Dist: pillow; extra == "doc"
Requires-Dist: openneuro-py>=2021.10.1; extra == "doc"
